odoo/addons/ssi_accountant_general_audit_ws_rr110/README.rst
odoo/addons/ssi_accountant_general_audit_ws_rr110/__init__.py
odoo/addons/ssi_accountant_general_audit_ws_rr110/__manifest__.py
odoo/addons/ssi_accountant_general_audit_ws_rr110/data/accountant_general_audit_worksheet_conclusion_data.xml
odoo/addons/ssi_accountant_general_audit_ws_rr110/data/accountant_general_audit_worksheet_type_data.xml
odoo/addons/ssi_accountant_general_audit_ws_rr110/data/approval_template_data.xml
odoo/addons/ssi_accountant_general_audit_ws_rr110/data/ir_sequence_data.xml
odoo/addons/ssi_accountant_general_audit_ws_rr110/data/policy_template_data.xml
odoo/addons/ssi_accountant_general_audit_ws_rr110/data/sequence_template_data.xml
odoo/addons/ssi_accountant_general_audit_ws_rr110/models/__init__.py
odoo/addons/ssi_accountant_general_audit_ws_rr110/models/ws_rr110.py
odoo/addons/ssi_accountant_general_audit_ws_rr110/models/ws_rr1101.py
odoo/addons/ssi_accountant_general_audit_ws_rr110/models/ws_rr1101_account.py
odoo/addons/ssi_accountant_general_audit_ws_rr110/models/ws_rr1101_account_comparison.py
odoo/addons/ssi_accountant_general_audit_ws_rr110/models/ws_rr1101_computation_comparison.py
odoo/addons/ssi_accountant_general_audit_ws_rr110/models/ws_rr1102.py
odoo/addons/ssi_accountant_general_audit_ws_rr110/models/ws_rr110_account.py
odoo/addons/ssi_accountant_general_audit_ws_rr110/security/ir.model.access.csv
odoo/addons/ssi_accountant_general_audit_ws_rr110/security/ir_module_category_data.xml
odoo/addons/ssi_accountant_general_audit_ws_rr110/security/ir_rule_data.xml
odoo/addons/ssi_accountant_general_audit_ws_rr110/security/res_group_data.xml
odoo/addons/ssi_accountant_general_audit_ws_rr110/static/description/icon.png
odoo/addons/ssi_accountant_general_audit_ws_rr110/views/ws_rr1101_views.xml
odoo/addons/ssi_accountant_general_audit_ws_rr110/views/ws_rr1102_views.xml
odoo/addons/ssi_accountant_general_audit_ws_rr110/views/ws_rr110_views.xml
odoo14_addon_ssi_accountant_general_audit_ws_rr110-14.0.1.3.2.dev1.dist-info/METADATA
odoo14_addon_ssi_accountant_general_audit_ws_rr110-14.0.1.3.2.dev1.dist-info/WHEEL
odoo14_addon_ssi_accountant_general_audit_ws_rr110-14.0.1.3.2.dev1.dist-info/top_level.txt
odoo14_addon_ssi_accountant_general_audit_ws_rr110-14.0.1.3.2.dev1.dist-info/RECORD
